pyiges/__init__.py
pyiges/check_imports.py
pyiges/constants.py
pyiges/entity.py
pyiges/faces.py
pyiges/geometry.py
pyiges/iges.py
pyiges/examples/__init__.py
pyiges/examples/impeller.igs
pyiges/examples/sample.igs
pyiges-0.3.2.dist-info/licenses/LICENSE
pyiges-0.3.2.dist-info/WHEEL
pyiges-0.3.2.dist-info/METADATA
pyiges-0.3.2.dist-info/RECORD
