Metadata-Version: 2.4
Name: pyiges
Version: 0.3.2
Summary: Pythonic IGES reader
Keywords: iges,cad,nurbs,bspline
Author-email: PyVista Developers <info@pyvista.org>
Requires-Python: >=3.9
Classifier: Development Status :: 4 - Beta
Classifier: Intended Audience :: Science/Research
Classifier: Topic :: Scientific/Engineering :: Information Analysis
Classifier: License :: OSI Approved :: MIT License
Classifier: Operating System :: Microsoft :: Windows
Classifier: Operating System :: POSIX
Classifier: Operating System :: MacOS
Classifier: Programming Language :: Python :: 3.9
Classifier: Programming Language :: Python :: 3.10
Classifier: Programming Language :: Python :: 3.11
Classifier: Programming Language :: Python :: 3.12
Classifier: Programming Language :: Python :: 3.13
License-File: LICENSE
Requires-Dist: tqdm
Requires-Dist: numpy
Requires-Dist: sphinx ; extra == "docs"
Requires-Dist: sphinx_rtd_theme ; extra == "docs"
Requires-Dist: sphinx-notfound-page ; extra == "docs"
Requires-Dist: sphinx-copybutton ; extra == "docs"
Requires-Dist: geomdl ; extra == "full"
Requires-Dist: pyvista>=0.28.0 ; extra == "full"
Requires-Dist: pytest ; extra == "test"
Requires-Dist: pytest-cov ; extra == "test"
Project-URL: Documentation, https://github.com/pyvista/pyiges
Project-URL: Homepage, https://github.com/pyvista/pyiges
Project-URL: Repository, https://github.com/pyvista/pyiges.git
Provides-Extra: docs
Provides-Extra: full
Provides-Extra: test
